bach/__init__.py
bach/dataframe.py
bach/expression.py
bach/from_database.py
bach/from_pandas.py
bach/indexing.py
bach/merge.py
bach/partitioning.py
bach/plotting.py
bach/py.typed
bach/quantile.py
bach/sample.py
bach/savepoints.py
bach/sql_model.py
bach/types.py
bach/types_bq.py
bach/utils.py
bach/display_formats/__init__.py
bach/display_formats/graph_display.py
bach/display_formats/markdown_display.py
bach/operations/__init__.py
bach/operations/concat.py
bach/operations/cut.py
bach/operations/describe.py
bach/operations/value_propagation.py
bach/preprocessing/__init__.py
bach/preprocessing/scalers.py
bach/series/__init__.py
bach/series/series.py
bach/series/series_boolean.py
bach/series/series_datetime.py
bach/series/series_dict.py
bach/series/series_json.py
bach/series/series_list.py
bach/series/series_multi_level.py
bach/series/series_numeric.py
bach/series/series_string.py
bach/series/series_uuid.py
bach/series/array_operations/__init__.py
bach/series/array_operations/flattening.py
bach/series/utils/__init__.py
bach/series/utils/datetime_formats.py
bach/testing/__init__.py
bach/testing/utils.py
sql_models/__init__.py
sql_models/cli_util.py
sql_models/constants.py
sql_models/graph_operations.py
sql_models/model.py
sql_models/py.typed
sql_models/sql_generator.py
sql_models/sql_query_parser.py
sql_models/util.py
objectiv_bach-0.0.28.dist-info/METADATA
objectiv_bach-0.0.28.dist-info/WHEEL
objectiv_bach-0.0.28.dist-info/top_level.txt
objectiv_bach-0.0.28.dist-info/RECORD
