Metadata-Version: 2.1
Name: objectiv-bach
Version: 0.0.28
Summary: Objectiv Bach provides Pandas-like DataFrames backed by SQL
Home-page: https://github.com/objectiv/objectiv-analytics/
Author: Objectiv B.V.
Author-email: hi@objectiv.io
License: Apache License 2.0
Project-URL: Documentation, https://objectiv.io/docs
Project-URL: Bug Tracker, https://github.com/objectiv/objectiv-analytics/issues
Classifier: Programming Language :: Python :: 3
Classifier: License :: OSI Approved :: Apache Software License
Classifier: Operating System :: OS Independent
Classifier: Development Status :: 4 - Beta
Requires-Python: >=3.7
Requires-Dist: sqlalchemy (<=1.4.27)
Requires-Dist: pyarrow (<7.0dev)
Requires-Dist: psycopg2-binary
Requires-Dist: pandas (>=1.3.1)
Requires-Dist: sqlparse
Provides-Extra: athena
Requires-Dist: pyathena (>=2.10.0) ; extra == 'athena'
Provides-Extra: bigquery
Requires-Dist: sqlalchemy-bigquery (>=1.4.0) ; extra == 'bigquery'
Requires-Dist: google-cloud-bigquery-storage ; extra == 'bigquery'
Provides-Extra: dev
Requires-Dist: pytest (==6.2.5) ; extra == 'dev'
Requires-Dist: pytest-xdist (==2.5.0) ; extra == 'dev'
Requires-Dist: pytest-timeout (==2.1.0) ; extra == 'dev'
Requires-Dist: mypy (==0.910) ; extra == 'dev'
Requires-Dist: pycodestyle (==2.7.0) ; extra == 'dev'
Requires-Dist: ipython (==7.31.1) ; extra == 'dev'
Requires-Dist: matplotlib (==3.5.1) ; extra == 'dev'
Requires-Dist: scikit-learn (==1.0.2) ; extra == 'dev'
Requires-Dist: python-dotenv (==0.20.0) ; extra == 'dev'
Requires-Dist: graphviz (==0.20.1) ; extra == 'dev'
